{
    "data": {},
    "data_type": "secondary_distributions",
    "languages": {},
    "secondary_sum": 3153,
    "simc_settings": {
        "class": "mage",
        "fight_style": "patchwerk",
        "iterations": "20000",
        "ptr": "1",
        "simc_hash": "928ddc3593",
        "spec": "frost",
        "target_error": "0.2",
        "tier": "22"
    },
    "sorted_data_keys": {},
    "subtitle": "UTC 2018-12-09 14:11 | SimC build: <a href=\"https://github.com/simulationcraft/simc/commit/928ddc3593\" target=\"blank\">928ddc3</a>",
    "timestamp": "2018-12-09 14:11",
    "title": "Secondary_Distributions | Frost Mage | Patchwerk"
}