{
    "data": {
        "3302022": {
            "10_10_10_70": 5816,
            "10_10_20_60": 6031,
            "10_10_30_50": 6232,
            "10_10_40_40": 6357,
            "10_10_50_30": 6442,
            "10_10_60_20": 6430,
            "10_10_70_10": 6366,
            "10_20_10_60": 6224,
            "10_20_20_50": 6464,
            "10_20_30_40": 6656,
            "10_20_40_30": 6770,
            "10_20_50_20": 6799,
            "10_20_60_10": 6780,
            "10_30_10_50": 6470,
            "10_30_20_40": 6703,
            "10_30_30_30": 6876,
            "10_30_40_20": 6942,
            "10_30_50_10": 6954,
            "10_40_10_40": 6673,
            "10_40_20_30": 6888,
            "10_40_30_20": 7002,
            "10_40_40_10": 7042,
            "10_50_10_30": 6716,
            "10_50_20_20": 6874,
            "10_50_30_10": 6980,
            "10_60_10_20": 6753,
            "10_60_20_10": 6881,
            "10_70_10_10": 6706,
            "20_10_10_60": 5917,
            "20_10_20_50": 6162,
            "20_10_30_40": 6332,
            "20_10_40_30": 6438,
            "20_10_50_20": 6487,
            "20_10_60_10": 6453,
            "20_20_10_50": 6348,
            "20_20_20_40": 6584,
            "20_20_30_30": 6742,
            "20_20_40_20": 6812,
            "20_20_50_10": 6832,
            "20_30_10_40": 6594,
            "20_30_20_30": 6813,
            "20_30_30_20": 6935,
            "20_30_40_10": 6972,
            "20_40_10_30": 6757,
            "20_40_20_20": 6942,
            "20_40_30_10": 7041,
            "20_50_10_20": 6772,
            "20_50_20_10": 6908,
            "20_60_10_10": 6774,
            "30_10_10_50": 6006,
            "30_10_20_40": 6226,
            "30_10_30_30": 6384,
            "30_10_40_20": 6470,
            "30_10_50_10": 6481,
            "30_20_10_40": 6407,
            "30_20_20_30": 6640,
            "30_20_30_20": 6762,
            "30_20_40_10": 6819,
            "30_30_10_30": 6635,
            "30_30_20_20": 6826,
            "30_30_30_10": 6907,
            "30_40_10_20": 6783,
            "30_40_20_10": 6930,
            "30_50_10_10": 6762,
            "40_10_10_40": 6039,
            "40_10_20_30": 6243,
            "40_10_30_20": 6359,
            "40_10_40_10": 6432,
            "40_20_10_30": 6437,
            "40_20_20_20": 6626,
            "40_20_30_10": 6729,
            "40_30_10_20": 6626,
            "40_30_20_10": 6787,
            "40_40_10_10": 6750,
            "50_10_10_30": 6040,
            "50_10_20_20": 6213,
            "50_10_30_10": 6304,
            "50_20_10_20": 6396,
            "50_20_20_10": 6554,
            "50_30_10_10": 6556,
            "60_10_10_20": 5981,
            "60_10_20_10": 6115,
            "60_20_10_10": 6299,
            "70_10_10_10": 5886
        }
    },
    "data_type": "secondary_distributions",
    "secondary_sum": 1620,
    "simc_settings": {
        "class": "warlock",
        "fight_style": "hecticaddcleave",
        "iterations": "250000",
        "ptr": "0",
        "simc_hash": "ae005ee6c7554f56dc7deeb227a5f68de612e148",
        "spec": "affliction",
        "target_error": "0.2",
        "tier": "21"
    },
    "sorted_data_keys": {
        "3302022": [
            "10_40_40_10",
            "20_40_30_10",
            "10_40_30_20",
            "10_50_30_10",
            "20_30_40_10",
            "10_30_50_10",
            "10_30_40_20",
            "20_40_20_20",
            "20_30_30_20",
            "30_40_20_10",
            "20_50_20_10",
            "30_30_30_10",
            "10_40_20_30",
            "10_60_20_10",
            "10_30_30_30",
            "10_50_20_20",
            "20_20_50_10",
            "30_30_20_20",
            "30_20_40_10",
            "20_30_20_30",
            "20_20_40_20",
            "10_20_50_20",
            "40_30_20_10",
            "30_40_10_20",
            "10_20_60_10",
            "20_60_10_10",
            "20_50_10_20",
            "10_20_40_30",
            "30_20_30_20",
            "30_50_10_10",
            "20_40_10_30",
            "10_60_10_20",
            "40_40_10_10",
            "20_20_30_30",
            "40_20_30_10",
            "10_50_10_30",
            "10_70_10_10",
            "10_30_20_40",
            "10_40_10_40",
            "10_20_30_40",
            "30_20_20_30",
            "30_30_10_30",
            "40_20_20_20",
            "40_30_10_20",
            "20_30_10_40",
            "20_20_20_40",
            "50_30_10_10",
            "50_20_20_10",
            "20_10_50_20",
            "30_10_50_10",
            "10_30_10_50",
            "30_10_40_20",
            "10_20_20_50",
            "20_10_60_10",
            "10_10_50_30",
            "20_10_40_30",
            "40_20_10_30",
            "40_10_40_10",
            "10_10_60_20",
            "30_20_10_40",
            "50_20_10_20",
            "30_10_30_30",
            "10_10_70_10",
            "40_10_30_20",
            "10_10_40_40",
            "20_20_10_50",
            "20_10_30_40",
            "50_10_30_10",
            "60_20_10_10",
            "40_10_20_30",
            "10_10_30_50",
            "30_10_20_40",
            "10_20_10_60",
            "50_10_20_20",
            "20_10_20_50",
            "60_10_20_10",
            "50_10_10_30",
            "40_10_10_40",
            "10_10_20_60",
            "30_10_10_50",
            "60_10_10_20",
            "20_10_10_60",
            "70_10_10_10",
            "10_10_10_70"
        ]
    },
    "subtitle": "UTC 2018-07-31 17:03 | SimC build: <a href=\"https://github.com/simulationcraft/simc/commit/ae005ee6c7554f56dc7deeb227a5f68de612e148\" target=\"blank\">ae005ee</a>",
    "timestamp": "2018-07-31 17:03",
    "title": "Secondary_Distributions | Warlock Affliction | Hecticaddcleave"
}