{
    "data": {
        "Archive of the Titans": {
            "1_340": 5338,
            "1_355": 5344,
            "1_370": 5350,
            "1_385": 5345,
            "2_385": 5340,
            "3_385": 5332
        },
        "Azerite Empowered": {
            "1_340": 5337,
            "1_355": 5343,
            "1_370": 5346,
            "1_385": 5328,
            "2_385": 5338,
            "3_385": 5344
        },
        "Azerite Globules": {
            "1_340": 5450,
            "1_355": 5467,
            "1_370": 5474,
            "1_385": 5504,
            "2_385": 5671,
            "3_385": 5833
        },
        "Barrage Of Many Bombs": {
            "1_340": 5335,
            "1_355": 5332,
            "1_370": 5346,
            "1_385": 5349,
            "2_385": 5331,
            "3_385": 5339
        },
        "Battlefield Focus": {
            "1_340": 5346,
            "1_355": 5342,
            "1_370": 5341,
            "1_385": 5321,
            "2_385": 5335,
            "3_385": 5353
        },
        "Blightborne Infusion": {
            "1_340": 5334,
            "1_355": 5341,
            "1_370": 5339,
            "1_385": 5336,
            "2_385": 5328,
            "3_385": 5343
        },
        "Blood Rite": {
            "1_340": 5521,
            "1_355": 5536,
            "1_370": 5540,
            "1_385": 5574,
            "2_385": 5764,
            "3_385": 5898
        },
        "Blood Siphon": {
            "1_340": 5693,
            "1_355": 5740,
            "1_370": 5799,
            "1_385": 5871,
            "2_385": 6403,
            "3_385": 6919
        },
        "Champion of Azeroth": {
            "1_340": 5816,
            "1_355": 5909,
            "1_370": 6007,
            "1_385": 6104,
            "2_385": 6932,
            "3_385": 7902
        },
        "Chorus of Insanity": {
            "1_340": 6004,
            "1_355": 6050,
            "1_370": 6099,
            "1_385": 6149,
            "2_385": 6777,
            "3_385": 7000
        },
        "Collective Will": {
            "1_340": 5343,
            "1_355": 5337,
            "1_370": 5343,
            "1_385": 5333,
            "2_385": 5343,
            "3_385": 5352
        },
        "Combined Might": {
            "1_340": 5338,
            "1_355": 5341,
            "1_370": 5351,
            "1_385": 5335,
            "2_385": 5332,
            "3_385": 5342
        },
        "Dagger in the Back": {
            "1_340": 5353,
            "1_355": 5344,
            "1_370": 5344,
            "1_385": 5332,
            "2_385": 5331,
            "3_385": 5344
        },
        "Death Throes": {
            "1_340": 5363,
            "1_355": 5387,
            "1_370": 5382,
            "1_385": 5382,
            "2_385": 5446,
            "3_385": 5484
        },
        "Earthlink": {
            "1_340": 5789,
            "1_355": 5867,
            "1_370": 5944,
            "1_385": 6042,
            "2_385": 6740,
            "3_385": 7416
        },
        "Elemental Whirl": {
            "1_340": 5605,
            "1_355": 5625,
            "1_370": 5639,
            "1_385": 5655,
            "2_385": 5961,
            "3_385": 6267
        },
        "Filthy Transfusion": {
            "1_340": 5681,
            "1_355": 5714,
            "1_370": 5783,
            "1_385": 5871,
            "2_385": 6358,
            "3_385": 6873
        },
        "Glory in Battle": {
            "1_340": 6318,
            "1_355": 6404,
            "1_370": 6494,
            "1_385": 6566,
            "2_385": 7993,
            "3_385": 8741
        },
        "Gutripper": {
            "1_340": 5342,
            "1_355": 5349,
            "1_370": 5334,
            "1_385": 5336,
            "2_385": 5347,
            "3_385": 5337
        },
        "Heed My Call": {
            "1_340": 5383,
            "1_355": 5372,
            "1_370": 5388,
            "1_385": 5401,
            "2_385": 5456,
            "3_385": 5520
        },
        "Incite the Pack": {
            "1_340": 5337,
            "1_355": 5341,
            "1_370": 5343,
            "1_385": 5343,
            "2_385": 5343,
            "3_385": 5345
        },
        "Laser Matrix": {
            "1_340": 5334,
            "1_355": 5333,
            "1_370": 5349,
            "1_385": 5344,
            "2_385": 5354,
            "3_385": 5346
        },
        "Meticulous Scheming": {
            "1_340": 5340,
            "1_355": 5334,
            "1_370": 5344,
            "1_385": 5337,
            "2_385": 5335,
            "3_385": 5350
        },
        "On My Way": {
            "1_340": 5701,
            "1_355": 5758,
            "1_370": 5838,
            "1_385": 5895,
            "2_385": 6458,
            "3_385": 7024
        },
        "Overwhelming Power": {
            "1_340": 5515,
            "1_355": 5529,
            "1_370": 5542,
            "1_385": 5556,
            "2_385": 5766,
            "3_385": 5919
        },
        "Relational Normalization Gizmo": {
            "1_340": 5326,
            "1_355": 5353,
            "1_370": 5336,
            "1_385": 5339,
            "2_385": 5340,
            "3_385": 5347
        },
        "Retaliatory Fury": {
            "1_340": 5687,
            "1_355": 5757,
            "1_370": 5814,
            "1_385": 5881,
            "2_385": 6403,
            "3_385": 6949
        },
        "Rezan's Fury": {
            "1_340": 5349,
            "1_355": 5347,
            "1_370": 5340,
            "1_385": 5335,
            "2_385": 5344,
            "3_385": 5344
        },
        "Ricocheting Inflatable Pyrosaw": {
            "1_340": 5349,
            "1_355": 5327,
            "1_370": 5345,
            "1_385": 5341,
            "2_385": 5354,
            "3_385": 5347
        },
        "Ruinous Bolt": {
            "1_340": 5339,
            "1_355": 5340,
            "1_370": 5339,
            "1_385": 5335,
            "2_385": 5337,
            "3_385": 5342
        },
        "Searing Dialogue": {
            "1_340": 5347,
            "1_355": 5323,
            "1_370": 5326,
            "1_385": 5332,
            "2_385": 5327,
            "3_385": 5353
        },
        "Secrets of the Deep": {
            "1_340": 5359,
            "1_355": 5345,
            "1_370": 5342,
            "1_385": 5334,
            "2_385": 5336,
            "3_385": 5337
        },
        "Spiteful Apparitions": {
            "1_340": 5420,
            "1_355": 5423,
            "1_370": 5440,
            "1_385": 5441,
            "2_385": 5560,
            "3_385": 5654
        },
        "Swirling Sands": {
            "1_340": 5347,
            "1_355": 5343,
            "1_370": 5328,
            "1_385": 5346,
            "2_385": 5331,
            "3_385": 5352
        },
        "Sylvanas' Resolve": {
            "1_340": 5704,
            "1_355": 5753,
            "1_370": 5815,
            "1_385": 5892,
            "2_385": 6426,
            "3_385": 6973
        },
        "Synaptic Spark Capacitor": {
            "1_340": 5343,
            "1_355": 5346,
            "1_370": 5343,
            "1_385": 5341,
            "2_385": 5343,
            "3_385": 5339
        },
        "Thought Harvester": {
            "1_340": 5412,
            "1_355": 5439,
            "1_370": 5433,
            "1_385": 5451,
            "2_385": 5573,
            "3_385": 5686
        },
        "Thunderous Blast": {
            "1_340": 5924,
            "1_355": 5983,
            "1_370": 6111,
            "1_385": 6224,
            "2_385": 7088,
            "3_385": 7967
        },
        "Tidal Surge": {
            "1_340": 5490,
            "1_355": 5525,
            "1_370": 5547,
            "1_385": 5580,
            "2_385": 5836,
            "3_385": 6082
        },
        "Tradewinds": {
            "1_340": 5336,
            "1_355": 5343,
            "1_370": 5345,
            "1_385": 5353,
            "2_385": 5334,
            "3_385": 5344
        },
        "Unstable Catalyst": {
            "1_340": 5336,
            "1_355": 5341,
            "1_370": 5330,
            "1_385": 5357,
            "2_385": 5343,
            "3_385": 5342
        },
        "Unstable Flames": {
            "1_340": 6099,
            "1_355": 6151,
            "1_370": 6197,
            "1_385": 6247,
            "2_385": 6815,
            "3_385": 7102
        },
        "Whispers of the Damned": {
            "1_340": 5956,
            "1_355": 6051,
            "1_370": 6138,
            "1_385": 6280,
            "2_385": 7249,
            "3_385": 8217
        },
        "baseline": {
            "1_340": 5342,
            "1_385": 5342
        }
    },
    "data_type": "azerite_traits",
    "simc_settings": {
        "class": "priest",
        "fight_style": "patchwerk",
        "iterations": "250000",
        "ptr": "0",
        "simc_hash": "ae005ee6c7554f56dc7deeb227a5f68de612e148",
        "spec": "shadow",
        "target_error": "0.2",
        "tier": "21"
    },
    "simulated_steps": [
        "1_385",
        "1_370",
        "1_355",
        "1_340"
    ],
    "sorted_data_keys": [
        "Glory in Battle",
        "Whispers of the Damned",
        "Unstable Flames",
        "Thunderous Blast",
        "Chorus of Insanity",
        "Champion of Azeroth",
        "Earthlink",
        "On My Way",
        "Sylvanas' Resolve",
        "Retaliatory Fury",
        "Blood Siphon",
        "Filthy Transfusion",
        "Elemental Whirl",
        "Tidal Surge",
        "Blood Rite",
        "Overwhelming Power",
        "Azerite Globules",
        "Thought Harvester",
        "Spiteful Apparitions",
        "Heed My Call",
        "Death Throes",
        "Unstable Catalyst",
        "Tradewinds",
        "Barrage Of Many Bombs",
        "Swirling Sands",
        "Archive of the Titans",
        "Laser Matrix",
        "Incite the Pack",
        "baseline",
        "Ricocheting Inflatable Pyrosaw",
        "Synaptic Spark Capacitor",
        "Relational Normalization Gizmo",
        "Meticulous Scheming",
        "Gutripper",
        "Blightborne Infusion",
        "Ruinous Bolt",
        "Rezan's Fury",
        "Combined Might",
        "Secrets of the Deep",
        "Collective Will",
        "Searing Dialogue",
        "Dagger in the Back",
        "Azerite Empowered",
        "Battlefield Focus"
    ],
    "sorted_data_keys_2": [
        "Glory in Battle",
        "Whispers of the Damned",
        "Thunderous Blast",
        "Champion of Azeroth",
        "Earthlink",
        "Unstable Flames",
        "On My Way",
        "Chorus of Insanity",
        "Sylvanas' Resolve",
        "Retaliatory Fury",
        "Blood Siphon",
        "Filthy Transfusion",
        "Elemental Whirl",
        "Tidal Surge",
        "Overwhelming Power",
        "Blood Rite",
        "Azerite Globules",
        "Thought Harvester",
        "Spiteful Apparitions",
        "Heed My Call",
        "Death Throes",
        "Searing Dialogue",
        "Battlefield Focus",
        "Swirling Sands",
        "Collective Will",
        "Meticulous Scheming",
        "Ricocheting Inflatable Pyrosaw",
        "Relational Normalization Gizmo",
        "Laser Matrix",
        "Incite the Pack",
        "Azerite Empowered",
        "Rezan's Fury",
        "Dagger in the Back",
        "Tradewinds",
        "Blightborne Infusion",
        "Ruinous Bolt",
        "Combined Might",
        "Unstable Catalyst",
        "Barrage Of Many Bombs",
        "Synaptic Spark Capacitor",
        "Gutripper",
        "Secrets of the Deep",
        "Archive of the Titans"
    ],
    "spell_ids": {
        "Archive of the Titans": "280555",
        "Azerite Empowered": "263978",
        "Azerite Globules": "266936",
        "Barrage Of Many Bombs": "280163",
        "Battlefield Focus": "280582",
        "Blightborne Infusion": "273823",
        "Blood Rite": "280407",
        "Blood Siphon": "264108",
        "Champion of Azeroth": "280710",
        "Chorus of Insanity": "278661",
        "Collective Will": "280581",
        "Combined Might": "280580",
        "Dagger in the Back": "280284",
        "Death Throes": "278659",
        "Earthlink": "279926",
        "Elemental Whirl": "263984",
        "Filthy Transfusion": "273834",
        "Glory in Battle": "280577",
        "Gutripper": "266937",
        "Heed My Call": "263987",
        "Incite the Pack": "280410",
        "Laser Matrix": "280559",
        "Meticulous Scheming": "273682",
        "On My Way": "267879",
        "Overwhelming Power": "266180",
        "Relational Normalization Gizmo": "280178",
        "Retaliatory Fury": "280579",
        "Rezan's Fury": "273790",
        "Ricocheting Inflatable Pyrosaw": "280168",
        "Ruinous Bolt": "273150",
        "Searing Dialogue": "272788",
        "Secrets of the Deep": "273829",
        "Spiteful Apparitions": "277682",
        "Swirling Sands": "280429",
        "Sylvanas' Resolve": "280598",
        "Synaptic Spark Capacitor": "280174",
        "Thought Harvester": "273319",
        "Thunderous Blast": "280380",
        "Tidal Surge": "280402",
        "Tradewinds": "281841",
        "Unstable Catalyst": "281514",
        "Unstable Flames": "279899",
        "Whispers of the Damned": "275722"
    },
    "subtitle": "UTC 2018-07-31 19:40 | SimC build: <a href=\"https://github.com/simulationcraft/simc/commit/ae005ee6c7554f56dc7deeb227a5f68de612e148\" target=\"blank\">ae005ee</a>",
    "timestamp": "2018-07-31 19:40",
    "title": "Azerite Traits | Priest Shadow | Patchwerk"
}