{
    "class_id": 6,
    "data": {
        "Blood of the Enemy +Breath of the Dying minor": 76575,
        "Blood of the Enemy +Condensed Life-Force minor": 75000,
        "Blood of the Enemy +Conflict and Strife minor": 76318,
        "Blood of the Enemy +Essence of the Focusing Iris minor": 76125,
        "Blood of the Enemy +Memory of Lucid Dreams minor": 77183,
        "Blood of the Enemy +Purification Protocol minor": 74204,
        "Blood of the Enemy +Ripple in Space minor": 73048,
        "Blood of the Enemy +Spark of Inspiration minor": 73837,
        "Blood of the Enemy +The Crucible of Flame minor": 75155,
        "Blood of the Enemy +The Formless Void minor": 75644,
        "Blood of the Enemy +The Unbound Force minor": 74357,
        "Blood of the Enemy +Vision of Perfection minor": 72388,
        "Blood of the Enemy +Worldvein Resonance minor": 74359,
        "Blood of the Enemy +Worldvein Resonance minor +3": 76623,
        "Breath of the Dying +Blood of the Enemy minor": 75547,
        "Breath of the Dying +Condensed Life-Force minor": 74687,
        "Breath of the Dying +Conflict and Strife minor": 76149,
        "Breath of the Dying +Essence of the Focusing Iris minor": 75900,
        "Breath of the Dying +Memory of Lucid Dreams minor": 76596,
        "Breath of the Dying +Purification Protocol minor": 73953,
        "Breath of the Dying +Ripple in Space minor": 72896,
        "Breath of the Dying +Spark of Inspiration minor": 74010,
        "Breath of the Dying +The Crucible of Flame minor": 74747,
        "Breath of the Dying +The Formless Void minor": 75329,
        "Breath of the Dying +The Unbound Force minor": 74383,
        "Breath of the Dying +Vision of Perfection minor": 72552,
        "Breath of the Dying +Worldvein Resonance minor": 74067,
        "Breath of the Dying +Worldvein Resonance minor +3": 76149,
        "Condensed Life-Force +Blood of the Enemy minor": 75142,
        "Condensed Life-Force +Breath of the Dying minor": 75835,
        "Condensed Life-Force +Conflict and Strife minor": 75683,
        "Condensed Life-Force +Essence of the Focusing Iris minor": 75497,
        "Condensed Life-Force +Memory of Lucid Dreams minor": 76395,
        "Condensed Life-Force +Purification Protocol minor": 73504,
        "Condensed Life-Force +Ripple in Space minor": 72560,
        "Condensed Life-Force +Spark of Inspiration minor": 73369,
        "Condensed Life-Force +The Crucible of Flame minor": 74391,
        "Condensed Life-Force +The Formless Void minor": 74887,
        "Condensed Life-Force +The Unbound Force minor": 73967,
        "Condensed Life-Force +Vision of Perfection minor": 72002,
        "Condensed Life-Force +Worldvein Resonance minor": 73719,
        "Condensed Life-Force +Worldvein Resonance minor +3": 75895,
        "Conflict and Strife +Blood of the Enemy minor": 73804,
        "Conflict and Strife +Breath of the Dying minor": 74688,
        "Conflict and Strife +Condensed Life-Force minor": 73103,
        "Conflict and Strife +Essence of the Focusing Iris minor": 74342,
        "Conflict and Strife +Memory of Lucid Dreams minor": 75093,
        "Conflict and Strife +Purification Protocol minor": 72363,
        "Conflict and Strife +Ripple in Space minor": 71276,
        "Conflict and Strife +Spark of Inspiration minor": 72029,
        "Conflict and Strife +The Crucible of Flame minor": 73156,
        "Conflict and Strife +The Formless Void minor": 73774,
        "Conflict and Strife +The Unbound Force minor": 72779,
        "Conflict and Strife +Vision of Perfection minor": 70400,
        "Conflict and Strife +Worldvein Resonance minor": 72598,
        "Conflict and Strife +Worldvein Resonance minor +3": 74796,
        "Essence of the Focusing Iris +Blood of the Enemy minor": 73857,
        "Essence of the Focusing Iris +Breath of the Dying minor": 74855,
        "Essence of the Focusing Iris +Condensed Life-Force minor": 73247,
        "Essence of the Focusing Iris +Conflict and Strife minor": 74605,
        "Essence of the Focusing Iris +Memory of Lucid Dreams minor": 75236,
        "Essence of the Focusing Iris +Purification Protocol minor": 72458,
        "Essence of the Focusing Iris +Ripple in Space minor": 71325,
        "Essence of the Focusing Iris +Spark of Inspiration minor": 72044,
        "Essence of the Focusing Iris +The Crucible of Flame minor": 73314,
        "Essence of the Focusing Iris +The Formless Void minor": 73735,
        "Essence of the Focusing Iris +The Unbound Force minor": 73112,
        "Essence of the Focusing Iris +Vision of Perfection minor": 70711,
        "Essence of the Focusing Iris +Worldvein Resonance minor": 72715,
        "Essence of the Focusing Iris +Worldvein Resonance minor +3": 74815,
        "Memory of Lucid Dreams +Blood of the Enemy minor": 75614,
        "Memory of Lucid Dreams +Breath of the Dying minor": 76208,
        "Memory of Lucid Dreams +Condensed Life-Force minor": 74619,
        "Memory of Lucid Dreams +Conflict and Strife minor": 75990,
        "Memory of Lucid Dreams +Essence of the Focusing Iris minor": 76150,
        "Memory of Lucid Dreams +Purification Protocol minor": 73881,
        "Memory of Lucid Dreams +Ripple in Space minor": 72886,
        "Memory of Lucid Dreams +Spark of Inspiration minor": 73271,
        "Memory of Lucid Dreams +The Crucible of Flame minor": 74722,
        "Memory of Lucid Dreams +The Formless Void minor": 75459,
        "Memory of Lucid Dreams +The Unbound Force minor": 74409,
        "Memory of Lucid Dreams +Vision of Perfection minor": 71429,
        "Memory of Lucid Dreams +Worldvein Resonance minor": 74213,
        "Memory of Lucid Dreams +Worldvein Resonance minor +3": 76527,
        "Purification Protocol +Blood of the Enemy minor": 71508,
        "Purification Protocol +Breath of the Dying minor": 72294,
        "Purification Protocol +Condensed Life-Force minor": 70714,
        "Purification Protocol +Conflict and Strife minor": 72124,
        "Purification Protocol +Essence of the Focusing Iris minor": 71851,
        "Purification Protocol +Memory of Lucid Dreams minor": 72735,
        "Purification Protocol +Ripple in Space minor": 69003,
        "Purification Protocol +Spark of Inspiration minor": 69702,
        "Purification Protocol +The Crucible of Flame minor": 70863,
        "Purification Protocol +The Formless Void minor": 71390,
        "Purification Protocol +The Unbound Force minor": 70437,
        "Purification Protocol +Vision of Perfection minor": 68250,
        "Purification Protocol +Worldvein Resonance minor": 70169,
        "Purification Protocol +Worldvein Resonance minor +3": 72268,
        "Ripple in Space +Blood of the Enemy minor": 70861,
        "Ripple in Space +Breath of the Dying minor": 71725,
        "Ripple in Space +Condensed Life-Force minor": 70197,
        "Ripple in Space +Conflict and Strife minor": 71473,
        "Ripple in Space +Essence of the Focusing Iris minor": 71221,
        "Ripple in Space +Memory of Lucid Dreams minor": 72173,
        "Ripple in Space +Purification Protocol minor": 69491,
        "Ripple in Space +Spark of Inspiration minor": 69097,
        "Ripple in Space +The Crucible of Flame minor": 70227,
        "Ripple in Space +The Formless Void minor": 70772,
        "Ripple in Space +The Unbound Force minor": 69860,
        "Ripple in Space +Vision of Perfection minor": 67819,
        "Ripple in Space +Worldvein Resonance minor": 69633,
        "Ripple in Space +Worldvein Resonance minor +3": 71763,
        "Spark of Inspiration +Blood of the Enemy minor": 69898,
        "Spark of Inspiration +Breath of the Dying minor": 70757,
        "Spark of Inspiration +Condensed Life-Force minor": 69234,
        "Spark of Inspiration +Conflict and Strife minor": 70483,
        "Spark of Inspiration +Essence of the Focusing Iris minor": 70312,
        "Spark of Inspiration +Memory of Lucid Dreams minor": 71319,
        "Spark of Inspiration +Purification Protocol minor": 68503,
        "Spark of Inspiration +Ripple in Space minor": 67500,
        "Spark of Inspiration +The Crucible of Flame minor": 69299,
        "Spark of Inspiration +The Formless Void minor": 69904,
        "Spark of Inspiration +The Unbound Force minor": 68906,
        "Spark of Inspiration +Vision of Perfection minor": 66954,
        "Spark of Inspiration +Worldvein Resonance minor": 68720,
        "Spark of Inspiration +Worldvein Resonance minor +3": 70831,
        "The Crucible of Flame +Blood of the Enemy minor": 73898,
        "The Crucible of Flame +Breath of the Dying minor": 74617,
        "The Crucible of Flame +Condensed Life-Force minor": 73141,
        "The Crucible of Flame +Conflict and Strife minor": 74397,
        "The Crucible of Flame +Essence of the Focusing Iris minor": 74245,
        "The Crucible of Flame +Memory of Lucid Dreams minor": 74861,
        "The Crucible of Flame +Purification Protocol minor": 72253,
        "The Crucible of Flame +Ripple in Space minor": 71392,
        "The Crucible of Flame +Spark of Inspiration minor": 72239,
        "The Crucible of Flame +The Formless Void minor": 73586,
        "The Crucible of Flame +The Unbound Force minor": 72864,
        "The Crucible of Flame +Vision of Perfection minor": 70682,
        "The Crucible of Flame +Worldvein Resonance minor": 72598,
        "The Crucible of Flame +Worldvein Resonance minor +3": 74614,
        "The Formless Void +Blood of the Enemy minor": 71608,
        "The Formless Void +Breath of the Dying minor": 72385,
        "The Formless Void +Condensed Life-Force minor": 70925,
        "The Formless Void +Conflict and Strife minor": 72179,
        "The Formless Void +Essence of the Focusing Iris minor": 71978,
        "The Formless Void +Memory of Lucid Dreams minor": 73082,
        "The Formless Void +Purification Protocol minor": 70134,
        "The Formless Void +Ripple in Space minor": 69038,
        "The Formless Void +Spark of Inspiration minor": 69844,
        "The Formless Void +The Crucible of Flame minor": 70963,
        "The Formless Void +The Unbound Force minor": 70558,
        "The Formless Void +Vision of Perfection minor": 68528,
        "The Formless Void +Worldvein Resonance minor": 70333,
        "The Formless Void +Worldvein Resonance minor +3": 72439,
        "The Unbound Force +Blood of the Enemy minor": 73014,
        "The Unbound Force +Breath of the Dying minor": 73837,
        "The Unbound Force +Condensed Life-Force minor": 72297,
        "The Unbound Force +Conflict and Strife minor": 73710,
        "The Unbound Force +Essence of the Focusing Iris minor": 73393,
        "The Unbound Force +Memory of Lucid Dreams minor": 74328,
        "The Unbound Force +Purification Protocol minor": 71586,
        "The Unbound Force +Ripple in Space minor": 70586,
        "The Unbound Force +Spark of Inspiration minor": 71478,
        "The Unbound Force +The Crucible of Flame minor": 72429,
        "The Unbound Force +The Formless Void minor": 72934,
        "The Unbound Force +Vision of Perfection minor": 70130,
        "The Unbound Force +Worldvein Resonance minor": 71762,
        "The Unbound Force +Worldvein Resonance minor +3": 73882,
        "Vision of Perfection +Blood of the Enemy minor": 71481,
        "Vision of Perfection +Breath of the Dying minor": 72372,
        "Vision of Perfection +Condensed Life-Force minor": 70816,
        "Vision of Perfection +Conflict and Strife minor": 71912,
        "Vision of Perfection +Essence of the Focusing Iris minor": 72141,
        "Vision of Perfection +Memory of Lucid Dreams minor": 71861,
        "Vision of Perfection +Purification Protocol minor": 69996,
        "Vision of Perfection +Ripple in Space minor": 68887,
        "Vision of Perfection +Spark of Inspiration minor": 69652,
        "Vision of Perfection +The Crucible of Flame minor": 70819,
        "Vision of Perfection +The Formless Void minor": 71395,
        "Vision of Perfection +The Unbound Force minor": 70438,
        "Vision of Perfection +Worldvein Resonance minor": 70165,
        "Vision of Perfection +Worldvein Resonance minor +3": 72401,
        "Worldvein Resonance +Blood of the Enemy minor": 75205,
        "Worldvein Resonance +Blood of the Enemy minor +3": 76736,
        "Worldvein Resonance +Breath of the Dying minor": 75951,
        "Worldvein Resonance +Breath of the Dying minor +3": 77287,
        "Worldvein Resonance +Condensed Life-Force minor": 74532,
        "Worldvein Resonance +Condensed Life-Force minor +3": 75823,
        "Worldvein Resonance +Conflict and Strife minor": 75903,
        "Worldvein Resonance +Conflict and Strife minor +3": 77276,
        "Worldvein Resonance +Essence of the Focusing Iris minor": 75682,
        "Worldvein Resonance +Essence of the Focusing Iris minor +3": 77077,
        "Worldvein Resonance +Memory of Lucid Dreams minor": 76672,
        "Worldvein Resonance +Memory of Lucid Dreams minor +3": 78097,
        "Worldvein Resonance +Purification Protocol minor": 73737,
        "Worldvein Resonance +Purification Protocol minor +3": 75035,
        "Worldvein Resonance +Ripple in Space minor": 72665,
        "Worldvein Resonance +Ripple in Space minor +3": 74025,
        "Worldvein Resonance +Spark of Inspiration minor": 73540,
        "Worldvein Resonance +Spark of Inspiration minor +3": 74956,
        "Worldvein Resonance +The Crucible of Flame minor": 74532,
        "Worldvein Resonance +The Crucible of Flame minor +3": 75868,
        "Worldvein Resonance +The Formless Void minor": 74956,
        "Worldvein Resonance +The Formless Void minor +3": 76376,
        "Worldvein Resonance +The Unbound Force minor": 74163,
        "Worldvein Resonance +The Unbound Force minor +3": 75410,
        "Worldvein Resonance +Vision of Perfection minor": 71571,
        "Worldvein Resonance +Vision of Perfection minor +3": 72943,
        "baseline": 66788
    },
    "data_type": "essence_combinations",
    "languages": {},
    "power_ids": {
        "3": 15,
        "Blood of the Enemy": 85,
        "Blood of the Enemy minor": 85,
        "Breath of the Dying": 135,
        "Breath of the Dying minor": 135,
        "Condensed Life-Force": 55,
        "Condensed Life-Force minor": 55,
        "Conflict and Strife": 123,
        "Conflict and Strife minor": 123,
        "Essence of the Focusing Iris": 19,
        "Essence of the Focusing Iris minor": 19,
        "Memory of Lucid Dreams": 104,
        "Memory of Lucid Dreams minor": 104,
        "Purification Protocol": 31,
        "Purification Protocol minor": 31,
        "Ripple in Space": 59,
        "Ripple in Space minor": 59,
        "Spark of Inspiration": 139,
        "Spark of Inspiration minor": 139,
        "The Crucible of Flame": 47,
        "The Crucible of Flame minor": 47,
        "The Formless Void": 143,
        "The Formless Void minor": 143,
        "The Unbound Force": 108,
        "The Unbound Force minor": 108,
        "Vision of Perfection": 81,
        "Vision of Perfection minor": 81,
        "Worldvein Resonance": 15,
        "Worldvein Resonance minor": 15
    },
    "profile": {
        "azerite_essences": "4:4:1/27:4:0/32:4:0/35:4:0",
        "back": {
            "bonus_id": "6286",
            "id": "169223"
        },
        "character": {
            "azerite_essences": "4:4:1/27:4:0/32:4:0/35:4:0",
            "class": "death_knight",
            "level": "120",
            "position": "back",
            "race": "blood_elf",
            "role": "attack",
            "spec": "frost",
            "talents": "3102013"
        },
        "chest": {
            "azerite_powers": "108/582/459/13",
            "bonus_id": "1517/4824/4775",
            "id": "174164"
        },
        "feet": {
            "bonus_id": "4824/1517",
            "id": "174173"
        },
        "finger1": {
            "bonus_id": "4824/1522",
            "enchant": "accord_of_mastery",
            "id": "169159"
        },
        "finger2": {
            "bonus_id": "4824/1522",
            "enchant": "accord_of_mastery",
            "id": "169157"
        },
        "hands": {
            "bonus_id": "4824/1517/6552",
            "id": "174169"
        },
        "head": {
            "azerite_powers": "108/582/459/13",
            "bonus_id": "4824/1517/4775",
            "id": "174163"
        },
        "items": {
            "back": {
                "bonus_id": "6286",
                "id": "169223"
            },
            "chest": {
                "azerite_powers": "108/582/459/13",
                "bonus_id": "1517/4824/4775",
                "id": "174164"
            },
            "feet": {
                "bonus_id": "4824/1517",
                "id": "174173"
            },
            "finger1": {
                "bonus_id": "4824/1522",
                "enchant": "accord_of_mastery",
                "id": "169159"
            },
            "finger2": {
                "bonus_id": "4824/1522",
                "enchant": "accord_of_mastery",
                "id": "169157"
            },
            "hands": {
                "bonus_id": "4824/1517/6552",
                "id": "174169"
            },
            "head": {
                "azerite_powers": "108/582/459/13",
                "bonus_id": "4824/1517/4775",
                "id": "174163"
            },
            "legs": {
                "bonus_id": "4824/1517",
                "id": "174172"
            },
            "main_hand": {
                "bonus_id": "4824/1517",
                "enchant": "rune_of_razorice",
                "id": "174109"
            },
            "neck": {
                "azerite_level": "80",
                "bonus_id": "4929/5814/4936/1630",
                "id": "158075"
            },
            "off_hand": {
                "bonus_id": "4824/1517",
                "enchant": "rune_of_the_fallen_crusader",
                "id": "174109"
            },
            "shoulders": {
                "azerite_powers": "108/582/459/13",
                "bonus_id": "1517/4824/4775",
                "id": "174165"
            },
            "trinket1": {
                "bonus_id": "4800/1517",
                "id": "169311"
            },
            "trinket2": {
                "bonus_id": "4800/1517",
                "id": "169314"
            },
            "waist": {
                "bonus_id": "4824/1517",
                "id": "174174"
            },
            "wrists": {
                "bonus_id": "4824/1517/6554",
                "id": "174177"
            }
        },
        "legs": {
            "bonus_id": "4824/1517",
            "id": "174172"
        },
        "level": "120",
        "main_hand": {
            "bonus_id": "4824/1517",
            "enchant": "rune_of_razorice",
            "id": "174109"
        },
        "neck": {
            "azerite_level": "80",
            "bonus_id": "4929/5814/4936/1630",
            "id": "158075"
        },
        "off_hand": {
            "bonus_id": "4824/1517",
            "enchant": "rune_of_the_fallen_crusader",
            "id": "174109"
        },
        "position": "back",
        "race": "blood_elf",
        "role": "attack",
        "shoulders": {
            "azerite_powers": "108/582/459/13",
            "bonus_id": "1517/4824/4775",
            "id": "174165"
        },
        "spec": "frost",
        "talents": "3102013",
        "trinket1": {
            "bonus_id": "4800/1517",
            "id": "169311"
        },
        "trinket2": {
            "bonus_id": "4800/1517",
            "id": "169314"
        },
        "waist": {
            "bonus_id": "4824/1517",
            "id": "174174"
        },
        "wrists": {
            "bonus_id": "4824/1517/6554",
            "id": "174177"
        }
    },
    "simc_settings": {
        "class": "death_knight",
        "fight_style": "patchwerk",
        "iterations": "20000",
        "ptr": "0",
        "simc_hash": "5c34735b34",
        "spec": "frost",
        "target_error": "0.1",
        "tier": "25"
    },
    "sorted_data_keys": [
        "Worldvein Resonance +Memory of Lucid Dreams minor +3",
        "Worldvein Resonance +Breath of the Dying minor +3",
        "Worldvein Resonance +Conflict and Strife minor +3",
        "Blood of the Enemy +Memory of Lucid Dreams minor",
        "Worldvein Resonance +Essence of the Focusing Iris minor +3",
        "Worldvein Resonance +Blood of the Enemy minor +3",
        "Worldvein Resonance +Memory of Lucid Dreams minor",
        "Blood of the Enemy +Worldvein Resonance minor +3",
        "Breath of the Dying +Memory of Lucid Dreams minor",
        "Blood of the Enemy +Breath of the Dying minor",
        "Memory of Lucid Dreams +Worldvein Resonance minor +3",
        "Condensed Life-Force +Memory of Lucid Dreams minor",
        "Worldvein Resonance +The Formless Void minor +3",
        "Blood of the Enemy +Conflict and Strife minor",
        "Memory of Lucid Dreams +Breath of the Dying minor",
        "Memory of Lucid Dreams +Essence of the Focusing Iris minor",
        "Breath of the Dying +Worldvein Resonance minor +3",
        "Breath of the Dying +Conflict and Strife minor",
        "Blood of the Enemy +Essence of the Focusing Iris minor",
        "Memory of Lucid Dreams +Conflict and Strife minor",
        "Worldvein Resonance +Breath of the Dying minor",
        "Worldvein Resonance +Conflict and Strife minor",
        "Breath of the Dying +Essence of the Focusing Iris minor",
        "Condensed Life-Force +Worldvein Resonance minor +3",
        "Worldvein Resonance +The Crucible of Flame minor +3",
        "Condensed Life-Force +Breath of the Dying minor",
        "Worldvein Resonance +Condensed Life-Force minor +3",
        "Condensed Life-Force +Conflict and Strife minor",
        "Worldvein Resonance +Essence of the Focusing Iris minor",
        "Blood of the Enemy +The Formless Void minor",
        "Memory of Lucid Dreams +Blood of the Enemy minor",
        "Breath of the Dying +Blood of the Enemy minor",
        "Condensed Life-Force +Essence of the Focusing Iris minor",
        "Memory of Lucid Dreams +The Formless Void minor",
        "Worldvein Resonance +The Unbound Force minor +3",
        "Breath of the Dying +The Formless Void minor",
        "Essence of the Focusing Iris +Memory of Lucid Dreams minor",
        "Worldvein Resonance +Blood of the Enemy minor",
        "Blood of the Enemy +The Crucible of Flame minor",
        "Condensed Life-Force +Blood of the Enemy minor",
        "Conflict and Strife +Memory of Lucid Dreams minor",
        "Worldvein Resonance +Purification Protocol minor +3",
        "Blood of the Enemy +Condensed Life-Force minor",
        "Worldvein Resonance +Spark of Inspiration minor +3",
        "Worldvein Resonance +The Formless Void minor",
        "Condensed Life-Force +The Formless Void minor",
        "The Crucible of Flame +Memory of Lucid Dreams minor",
        "Essence of the Focusing Iris +Breath of the Dying minor",
        "Essence of the Focusing Iris +Worldvein Resonance minor +3",
        "Conflict and Strife +Worldvein Resonance minor +3",
        "Breath of the Dying +The Crucible of Flame minor",
        "Memory of Lucid Dreams +The Crucible of Flame minor",
        "Conflict and Strife +Breath of the Dying minor",
        "Breath of the Dying +Condensed Life-Force minor",
        "Memory of Lucid Dreams +Condensed Life-Force minor",
        "The Crucible of Flame +Breath of the Dying minor",
        "The Crucible of Flame +Worldvein Resonance minor +3",
        "Essence of the Focusing Iris +Conflict and Strife minor",
        "Worldvein Resonance +The Crucible of Flame minor",
        "Worldvein Resonance +Condensed Life-Force minor",
        "Memory of Lucid Dreams +The Unbound Force minor",
        "The Crucible of Flame +Conflict and Strife minor",
        "Condensed Life-Force +The Crucible of Flame minor",
        "Breath of the Dying +The Unbound Force minor",
        "Blood of the Enemy +Worldvein Resonance minor",
        "Blood of the Enemy +The Unbound Force minor",
        "Conflict and Strife +Essence of the Focusing Iris minor",
        "The Unbound Force +Memory of Lucid Dreams minor",
        "The Crucible of Flame +Essence of the Focusing Iris minor",
        "Memory of Lucid Dreams +Worldvein Resonance minor",
        "Blood of the Enemy +Purification Protocol minor",
        "Worldvein Resonance +The Unbound Force minor",
        "Breath of the Dying +Worldvein Resonance minor",
        "Worldvein Resonance +Ripple in Space minor +3",
        "Breath of the Dying +Spark of Inspiration minor",
        "Condensed Life-Force +The Unbound Force minor",
        "Breath of the Dying +Purification Protocol minor",
        "The Crucible of Flame +Blood of the Enemy minor",
        "The Unbound Force +Worldvein Resonance minor +3",
        "Memory of Lucid Dreams +Purification Protocol minor",
        "Essence of the Focusing Iris +Blood of the Enemy minor",
        "Blood of the Enemy +Spark of Inspiration minor",
        "The Unbound Force +Breath of the Dying minor",
        "Conflict and Strife +Blood of the Enemy minor",
        "Conflict and Strife +The Formless Void minor",
        "Worldvein Resonance +Purification Protocol minor",
        "Essence of the Focusing Iris +The Formless Void minor",
        "Condensed Life-Force +Worldvein Resonance minor",
        "The Unbound Force +Conflict and Strife minor",
        "The Crucible of Flame +The Formless Void minor",
        "Worldvein Resonance +Spark of Inspiration minor",
        "Condensed Life-Force +Purification Protocol minor",
        "The Unbound Force +Essence of the Focusing Iris minor",
        "Condensed Life-Force +Spark of Inspiration minor",
        "Essence of the Focusing Iris +The Crucible of Flame minor",
        "Memory of Lucid Dreams +Spark of Inspiration minor",
        "Essence of the Focusing Iris +Condensed Life-Force minor",
        "Conflict and Strife +The Crucible of Flame minor",
        "The Crucible of Flame +Condensed Life-Force minor",
        "Essence of the Focusing Iris +The Unbound Force minor",
        "Conflict and Strife +Condensed Life-Force minor",
        "The Formless Void +Memory of Lucid Dreams minor",
        "Blood of the Enemy +Ripple in Space minor",
        "The Unbound Force +Blood of the Enemy minor",
        "Worldvein Resonance +Vision of Perfection minor +3",
        "The Unbound Force +The Formless Void minor",
        "Breath of the Dying +Ripple in Space minor",
        "Memory of Lucid Dreams +Ripple in Space minor",
        "The Crucible of Flame +The Unbound Force minor",
        "Conflict and Strife +The Unbound Force minor",
        "Purification Protocol +Memory of Lucid Dreams minor",
        "Essence of the Focusing Iris +Worldvein Resonance minor",
        "Worldvein Resonance +Ripple in Space minor",
        "The Crucible of Flame +Worldvein Resonance minor",
        "Conflict and Strife +Worldvein Resonance minor",
        "Condensed Life-Force +Ripple in Space minor",
        "Breath of the Dying +Vision of Perfection minor",
        "Essence of the Focusing Iris +Purification Protocol minor",
        "The Formless Void +Worldvein Resonance minor +3",
        "The Unbound Force +The Crucible of Flame minor",
        "Vision of Perfection +Worldvein Resonance minor +3",
        "Blood of the Enemy +Vision of Perfection minor",
        "The Formless Void +Breath of the Dying minor",
        "Vision of Perfection +Breath of the Dying minor",
        "Conflict and Strife +Purification Protocol minor",
        "The Unbound Force +Condensed Life-Force minor",
        "Purification Protocol +Breath of the Dying minor",
        "Purification Protocol +Worldvein Resonance minor +3",
        "The Crucible of Flame +Purification Protocol minor",
        "The Crucible of Flame +Spark of Inspiration minor",
        "The Formless Void +Conflict and Strife minor",
        "Ripple in Space +Memory of Lucid Dreams minor",
        "Vision of Perfection +Essence of the Focusing Iris minor",
        "Purification Protocol +Conflict and Strife minor",
        "Essence of the Focusing Iris +Spark of Inspiration minor",
        "Conflict and Strife +Spark of Inspiration minor",
        "Condensed Life-Force +Vision of Perfection minor",
        "The Formless Void +Essence of the Focusing Iris minor",
        "Vision of Perfection +Conflict and Strife minor",
        "Vision of Perfection +Memory of Lucid Dreams minor",
        "Purification Protocol +Essence of the Focusing Iris minor",
        "Ripple in Space +Worldvein Resonance minor +3",
        "The Unbound Force +Worldvein Resonance minor",
        "Ripple in Space +Breath of the Dying minor",
        "The Formless Void +Blood of the Enemy minor",
        "The Unbound Force +Purification Protocol minor",
        "Worldvein Resonance +Vision of Perfection minor",
        "Purification Protocol +Blood of the Enemy minor",
        "Vision of Perfection +Blood of the Enemy minor",
        "The Unbound Force +Spark of Inspiration minor",
        "Ripple in Space +Conflict and Strife minor",
        "Memory of Lucid Dreams +Vision of Perfection minor",
        "Vision of Perfection +The Formless Void minor",
        "The Crucible of Flame +Ripple in Space minor",
        "Purification Protocol +The Formless Void minor",
        "Essence of the Focusing Iris +Ripple in Space minor",
        "Spark of Inspiration +Memory of Lucid Dreams minor",
        "Conflict and Strife +Ripple in Space minor",
        "Ripple in Space +Essence of the Focusing Iris minor",
        "The Formless Void +The Crucible of Flame minor",
        "The Formless Void +Condensed Life-Force minor",
        "Purification Protocol +The Crucible of Flame minor",
        "Ripple in Space +Blood of the Enemy minor",
        "Spark of Inspiration +Worldvein Resonance minor +3",
        "Vision of Perfection +The Crucible of Flame minor",
        "Vision of Perfection +Condensed Life-Force minor",
        "Ripple in Space +The Formless Void minor",
        "Spark of Inspiration +Breath of the Dying minor",
        "Purification Protocol +Condensed Life-Force minor",
        "Essence of the Focusing Iris +Vision of Perfection minor",
        "The Crucible of Flame +Vision of Perfection minor",
        "The Unbound Force +Ripple in Space minor",
        "The Formless Void +The Unbound Force minor",
        "Spark of Inspiration +Conflict and Strife minor",
        "Vision of Perfection +The Unbound Force minor",
        "Purification Protocol +The Unbound Force minor",
        "Conflict and Strife +Vision of Perfection minor",
        "The Formless Void +Worldvein Resonance minor",
        "Spark of Inspiration +Essence of the Focusing Iris minor",
        "Ripple in Space +The Crucible of Flame minor",
        "Ripple in Space +Condensed Life-Force minor",
        "Purification Protocol +Worldvein Resonance minor",
        "Vision of Perfection +Worldvein Resonance minor",
        "The Formless Void +Purification Protocol minor",
        "The Unbound Force +Vision of Perfection minor",
        "Vision of Perfection +Purification Protocol minor",
        "Spark of Inspiration +The Formless Void minor",
        "Spark of Inspiration +Blood of the Enemy minor",
        "Ripple in Space +The Unbound Force minor",
        "The Formless Void +Spark of Inspiration minor",
        "Purification Protocol +Spark of Inspiration minor",
        "Vision of Perfection +Spark of Inspiration minor",
        "Ripple in Space +Worldvein Resonance minor",
        "Ripple in Space +Purification Protocol minor",
        "Spark of Inspiration +The Crucible of Flame minor",
        "Spark of Inspiration +Condensed Life-Force minor",
        "Ripple in Space +Spark of Inspiration minor",
        "The Formless Void +Ripple in Space minor",
        "Purification Protocol +Ripple in Space minor",
        "Spark of Inspiration +The Unbound Force minor",
        "Vision of Perfection +Ripple in Space minor",
        "Spark of Inspiration +Worldvein Resonance minor",
        "The Formless Void +Vision of Perfection minor",
        "Spark of Inspiration +Purification Protocol minor",
        "Purification Protocol +Vision of Perfection minor",
        "Ripple in Space +Vision of Perfection minor",
        "Spark of Inspiration +Ripple in Space minor",
        "Spark of Inspiration +Vision of Perfection minor"
    ],
    "spec_id": 251,
    "spell_ids": {
        "Blood of the Enemy": 298277,
        "Blood of the Enemy minor": 298275,
        "Breath of the Dying": "311195",
        "Breath of the Dying minor": "311198",
        "Condensed Life-Force": 299358,
        "Condensed Life-Force minor": 299357,
        "Conflict and Strife": 304121,
        "Conflict and Strife minor": 304123,
        "Essence of the Focusing Iris": 299338,
        "Essence of the Focusing Iris minor": 299337,
        "Memory of Lucid Dreams": 299374,
        "Memory of Lucid Dreams minor": 299373,
        "Purification Protocol": 299347,
        "Purification Protocol minor": 299346,
        "Ripple in Space": 302983,
        "Ripple in Space minor": 302985,
        "Spark of Inspiration": "311303",
        "Spark of Inspiration minor": "311306",
        "The Crucible of Flame": 299353,
        "The Crucible of Flame minor": 299350,
        "The Formless Void": "313922",
        "The Formless Void minor": "313920",
        "The Unbound Force": 299378,
        "The Unbound Force minor": 299377,
        "Vision of Perfection": 299370,
        "Vision of Perfection minor": 299369,
        "Worldvein Resonance": 299334
    },
    "subtitle": "UTC 2020-04-23 20:03 | SimC build: <a href=\"https://github.com/simulationcraft/simc/commit/5c34735b34\" target=\"blank\">5c34735</a>",
    "talent_data": {
        "1": {
            "1": {
                "name": "Inexorable Assault",
                "spell_id": "253593"
            },
            "2": {
                "name": "Icy Talons",
                "spell_id": "194878"
            },
            "3": {
                "name": "Cold Heart",
                "spell_id": "281208"
            }
        },
        "2": {
            "1": {
                "name": "Runic Attenuation",
                "spell_id": "207104"
            },
            "2": {
                "name": "Murderous Efficiency",
                "spell_id": "207061"
            },
            "3": {
                "name": "Horn of Winter",
                "spell_id": "57330"
            }
        },
        "3": {
            "1": {
                "name": "Death's Reach",
                "spell_id": "276079"
            },
            "2": {
                "name": "Asphyxiate",
                "spell_id": "108194"
            },
            "3": {
                "name": "Blinding Sleet",
                "spell_id": "207167"
            }
        },
        "4": {
            "1": {
                "name": "Avalanche",
                "spell_id": "207142"
            },
            "2": {
                "name": "Frozen Pulse",
                "spell_id": "194909"
            },
            "3": {
                "name": "Frostscythe",
                "spell_id": "207230"
            }
        },
        "5": {
            "1": {
                "name": "Permafrost",
                "spell_id": "207200"
            },
            "2": {
                "name": "Wraith Walk",
                "spell_id": "212552"
            },
            "3": {
                "name": "Death Pact",
                "spell_id": "48743"
            }
        },
        "6": {
            "1": {
                "name": "Gathering Storm",
                "spell_id": "194912"
            },
            "2": {
                "name": "Glacial Advance",
                "spell_id": "194913"
            },
            "3": {
                "name": "Frostwyrm's Fury",
                "spell_id": "279302"
            }
        },
        "7": {
            "1": {
                "name": "Icecap",
                "spell_id": "207126"
            },
            "2": {
                "name": "Obliteration",
                "spell_id": "281238"
            },
            "3": {
                "name": "Breath of Sindragosa",
                "spell_id": "152279"
            }
        }
    },
    "timestamp": "2020-04-23 20:03",
    "title": "Essence Combinations | Frost Death Knight | Patchwerk"
}