{
    "data": {},
    "data_type": "races",
    "simc_settings": {
        "class": "demon_hunter",
        "fight_style": "hecticaddcleave",
        "iterations": "250000",
        "ptr": "0",
        "simc_hash": "86fef239ee3f4cae015354fbf228952c0dddcb23",
        "spec": "havoc",
        "target_error": "0.2",
        "tier": "21"
    },
    "sorted_data_keys": [],
    "subtitle": "UTC 2018-07-20 23:52 | SimC build: <a href=\"https://github.com/simulationcraft/simc/commit/86fef239ee3f4cae015354fbf228952c0dddcb23\" target=\"blank\">86fef23</a>",
    "timestamp": "2018-07-20 23:52",
    "title": "Races | Demon_Hunter Havoc | Hecticaddcleave"
}